unicodeitplus/__init__.py
unicodeitplus/_make_data.py
unicodeitplus/cli.py
unicodeitplus/data.py
unicodeitplus/parser.py
unicodeitplus/transform.py
unicodeitplus-0.3.1.dist-info/LICENSE
unicodeitplus-0.3.1.dist-info/METADATA
unicodeitplus-0.3.1.dist-info/WHEEL
unicodeitplus-0.3.1.dist-info/entry_points.txt
unicodeitplus-0.3.1.dist-info/top_level.txt
unicodeitplus-0.3.1.dist-info/RECORD
