Metadata-Version: 2.1
Name: unicodeitplus
Version: 0.3.1
Summary: Converts simple LaTeX to an unicode approximation
Maintainer: Hans Dembinski
Maintainer-email: hans.dembinski@gmail.com
License: BSD 3-Clause License
Project-URL: repository, https://github.com/HDembinski/unicodeitplus
Classifier: Programming Language :: Python :: 3
Classifier: Operating System :: POSIX :: Linux
Classifier: Operating System :: MacOS
Classifier: Operating System :: Microsoft :: Windows
Classifier: Topic :: Scientific/Engineering
Classifier: Intended Audience :: Developers
Requires-Python: >=3.8
License-File: LICENSE
Requires-Dist: lark
Provides-Extra: test
Requires-Dist: pytest ; extra == 'test'
